excel_model_runner/__init__.py
excel_model_runner/command.py
excel_model_runner/run-excel-model
excel_model_runner-0.1.0.dist-info/entry_points.txt
excel_model_runner-0.1.0.dist-info/LICENSE
excel_model_runner-0.1.0.dist-info/WHEEL
excel_model_runner-0.1.0.dist-info/METADATA
excel_model_runner-0.1.0.dist-info/RECORD
