Metadata-Version: 2.1
Name: excel-model-runner
Version: 0.1.0
Summary: Runs an Excel model (.xlsx) with parameters
Home-page: https://github.com/dojo-modeling/excel-model-runner
License: MIT
Author: Matthew Printz
Author-email: matt@jataware.com
Requires-Python: >=3.8,<4.0
Classifier: Development Status :: 3 - Alpha
Classifier: Environment :: Console
Classifier: Intended Audience :: Information Technology
Classifier: Intended Audience :: Science/Research
Classifier: License :: OSI Approved :: MIT License
Classifier: Programming Language :: Python :: 3
Classifier: Programming Language :: Python :: 3.10
Classifier: Programming Language :: Python :: 3.8
Classifier: Programming Language :: Python :: 3.9
Classifier: Topic :: Office/Business :: Financial :: Spreadsheet
Classifier: Topic :: Scientific/Engineering
Classifier: Topic :: Scientific/Engineering :: Information Analysis
Requires-Dist: click (>=8.0.4,<9.0.0)
Requires-Dist: formulas (>=1.2.2,<2.0.0)
Requires-Dist: openpyxl (>=3.0.9,<4.0.0)
Project-URL: Repository, https://github.com/dojo-modeling/excel-model-runner
